harissa/__init__.py
harissa/inference/__init__.py
harissa/inference/kinetics.py
harissa/inference/network.py
harissa/inference/network_fast.py
harissa/model/__init__.py
harissa/model/base.py
harissa/model/cascade.py
harissa/model/tree.py
harissa/models/__init__.py
harissa/models/_checks.py
harissa/models/bursty_base.py
harissa/simulation/__init__.py
harissa/simulation/base.py
harissa/simulation/ode.py
harissa/simulation/pdmp.py
harissa/simulation/pdmp_fast.py
harissa/utils/__init__.py
harissa/utils/coupling.py
harissa/utils/plot_network.py
harissa/utils/processing.py
harissa-3.1.2.dist-info/METADATA
harissa-3.1.2.dist-info/WHEEL
harissa-3.1.2.dist-info/licenses/LICENSE.txt
harissa-3.1.2.dist-info/RECORD
