Metadata-Version: 2.4
Name: harissa
Version: 3.1.2
Summary: Simulation and inference of gene regulatory networks based on transcriptional bursting
Project-URL: Homepage, https://github.com/ulysseherbach/harissa
Author-email: Ulysse Herbach <ulysse.herbach@inria.fr>
License-File: LICENSE.txt
Classifier: License :: OSI Approved :: BSD License
Classifier: Operating System :: OS Independent
Classifier: Programming Language :: Python :: 3
Requires-Python: >=3.10
Requires-Dist: matplotlib>=3.8
Requires-Dist: networkx>=3.3
Requires-Dist: numba>=0.60
Requires-Dist: numpy>=1.26
Requires-Dist: scipy>=1.13
